README.rst
setup.py
markdown_i18n/__init__.py
markdown_i18n/extension.py
markdown_i18n/parser.py
markdown_i18n.egg-info/PKG-INFO
markdown_i18n.egg-info/SOURCES.txt
markdown_i18n.egg-info/dependency_links.txt
markdown_i18n.egg-info/requires.txt
markdown_i18n.egg-info/top_level.txt
tests/__init__.py
tests/test_i18n.py