Metadata-Version: 1.0
Name: markdown-i18n
Version: 3.0.0
Summary: i18n extension for Python Markdown
Home-page: https://github.com/gisce/markdown-i18n
Author: GISCE-TI, S.L.
Author-email: devel@gisce.net
License: MIT
Platform: UNKNOWN
